mvola/__init__.py
mvola/core.py
mvola/tools.py
mvola-1.0.5.dist-info/LICENSE
mvola-1.0.5.dist-info/METADATA
mvola-1.0.5.dist-info/WHEEL
mvola-1.0.5.dist-info/top_level.txt
mvola-1.0.5.dist-info/RECORD
