Metadata-Version: 2.1
Name: mvola
Version: 1.0.5
Summary: Mvola is a light open source module for your Mvola API.
Home-page: https://github.com/rivo2302/Mvola
Author: rivo2302
Author-email: rivo2302@gmail.com
License: UNKNOWN
Project-URL: Homepage, https://github.com/rivo2302/Mvola
Platform: UNKNOWN
Classifier: Programming Language :: Python :: 3
Classifier: Programming Language :: Python :: 3.7
Classifier: Programming Language :: Python :: 3.8
Classifier: Programming Language :: Python :: 3.9
Classifier: Programming Language :: Python :: 3.10
Classifier: License :: OSI Approved :: MIT License
Classifier: Operating System :: OS Independent
Requires-Python: >=3.7
